linchackathon/__init__.py
linchackathon/auth.py
linchackathon/ipaddr.py
linchackathon/orders.py
linchackathon/private.py
linchackathon/public.py
linchackathon/stoploss.py
linchackathon-0.1.3.dist-info/AUTHORS.rst
linchackathon-0.1.3.dist-info/LICENSE
linchackathon-0.1.3.dist-info/METADATA
linchackathon-0.1.3.dist-info/WHEEL
linchackathon-0.1.3.dist-info/entry_points.txt
linchackathon-0.1.3.dist-info/top_level.txt
linchackathon-0.1.3.dist-info/RECORD
