Metadata-Version: 2.1
Name: linchackathon
Version: 0.1.3
Summary: A package needed to participate i's Hackathon
Home-page: https://github.com/YasserMahfoud/linchackathon
Author: Yasser Mahfoud
Author-email: yassermahfoud1995@gmail.com
License: MIT license
Keywords: linchackathon
Platform: UNKNOWN
Classifier: Development Status :: 2 - Pre-Alpha
Classifier: Intended Audience :: Developers
Classifier: License :: OSI Approved :: MIT License
Classifier: Natural Language :: English
Classifier: Programming Language :: Python :: 3.6
Classifier: Programming Language :: Python :: 3.7
Classifier: Programming Language :: Python :: 3.8
Requires-Python: >=3.5
Requires-Dist: Click (>=7.0)
Requires-Dist: requests (>=2.0.0)
Requires-Dist: pandas (>=0.25.3)
Requires-Dist: numpy (>=1.18.0)
